snapdroid/__init__.py
snapdroid/__main__.py
snapdroid/snapdroid.py
snapdroid-1.0.4.dist-info/licenses/LICENSE
snapdroid-1.0.4.dist-info/METADATA
snapdroid-1.0.4.dist-info/WHEEL
snapdroid-1.0.4.dist-info/entry_points.txt
snapdroid-1.0.4.dist-info/top_level.txt
snapdroid-1.0.4.dist-info/RECORD
