Metadata-Version: 2.4
Name: snapdroid
Version: 1.0.4
Summary: Android Screenshot and Screen Recording Tool
Home-page: https://github.com/dr34mhacks/snapdroid
Author: Siddharth Joshi
Keywords: android,screenshot,screen recording,adb,testing,security
Classifier: Development Status :: 4 - Beta
Classifier: Environment :: Console
Classifier: Intended Audience :: Developers
Classifier: Intended Audience :: Information Technology
Classifier: License :: OSI Approved :: MIT License
Classifier: Operating System :: OS Independent
Classifier: Programming Language :: Python :: 3
Classifier: Topic :: Utilities
Classifier: Topic :: Software Development :: Testing
Classifier: Topic :: System :: Monitoring
Requires-Python: >=3.6
License-File: LICENSE
Dynamic: author
Dynamic: classifier
Dynamic: description
Dynamic: description-content-type
Dynamic: home-page
Dynamic: keywords
Dynamic: license-file
Dynamic: requires-python
Dynamic: summary
